featureSelection/__init__.py
featureSelection/featureSelector.py
featureSelection/load_dataset.py
featureSelection/utils.py
ml_featselect/__init__.py
ml_featselect/feature_selector.py
ml_featselect/load_dataset.py
ml_featselect/utils.py
ml_feature_selector-0.1.3.dist-info/LICENSE
ml_feature_selector-0.1.3.dist-info/METADATA
ml_feature_selector-0.1.3.dist-info/WHEEL
ml_feature_selector-0.1.3.dist-info/top_level.txt
ml_feature_selector-0.1.3.dist-info/RECORD
